badb/__init__.py
badb/__main__.py
badb/questionnaire.py
badb-0.0.8.dist-info/METADATA
badb-0.0.8.dist-info/WHEEL
badb-0.0.8.dist-info/entry_points.txt
badb-0.0.8.dist-info/licenses/LICENSE
badb-0.0.8.dist-info/RECORD
